pygraham/__init__.py
pygraham/main.py
pygraham/pygraham.py
pygraham-0.0.15.dist-info/METADATA
pygraham-0.0.15.dist-info/WHEEL
pygraham-0.0.15.dist-info/top_level.txt
pygraham-0.0.15.dist-info/RECORD
