Metadata-Version: 2.1
Name: pygraham
Version: 0.0.15
Summary: functional methods for python data structures
Home-page: https://github.com/riccardobernardi/PyGraham
Author: Bernardi Riccardo
Author-email: riccardo.bernardi@rocketmail.com
License: UNKNOWN
Platform: UNKNOWN
Classifier: Programming Language :: Python :: 3
Classifier: License :: OSI Approved :: MIT License
Classifier: Operating System :: OS Independent
